jelkasim/__init__.py
jelkasim/__main__.py
jelkasim/info_parser.py
jelkasim/main.py
jelkasim/read_non_blocking.py
jelkasim/simulator.py
jelkasim-1.2.0.dist-info/METADATA
jelkasim-1.2.0.dist-info/WHEEL
jelkasim-1.2.0.dist-info/entry_points.txt
jelkasim-1.2.0.dist-info/licenses/LICENSE
jelkasim-1.2.0.dist-info/RECORD
