Metadata-Version: 2.4
Name: jelkasim
Version: 1.2.0
Summary: Simulation for running Jelka FMF patterns
Project-URL: Homepage, https://github.com/Jelka-FMF/JelkaSim
Project-URL: Issues, https://github.com/Jelka-FMF/JelkaSim/issues
Author-email: Jošt Smrtnik <jost.smrtnik@gmail.com>, Filip Štamcar <projects@filips.si>
License-File: LICENSE
Classifier: Development Status :: 5 - Production/Stable
Classifier: License :: OSI Approved :: MIT License
Classifier: Operating System :: OS Independent
Classifier: Programming Language :: Python :: 3
Requires-Python: >=3.8
Requires-Dist: jelka-validator
Requires-Dist: pygame
